clickhouse_provider/__init__.py
clickhouse_provider/hooks/__init__.py
clickhouse_provider/hooks/clickhouse_hook.py
clickhouse_provider/operators/__init__.py
clickhouse_provider/operators/clickhouse_operator.py
airflow_provider_clickhouse-1.0.1.dist-info/LICENSE
airflow_provider_clickhouse-1.0.1.dist-info/METADATA
airflow_provider_clickhouse-1.0.1.dist-info/WHEEL
airflow_provider_clickhouse-1.0.1.dist-info/entry_points.txt
airflow_provider_clickhouse-1.0.1.dist-info/top_level.txt
airflow_provider_clickhouse-1.0.1.dist-info/RECORD
